flake8_module_name.py
flake8_module_name-0.2.0.dist-info/METADATA
flake8_module_name-0.2.0.dist-info/RECORD
flake8_module_name-0.2.0.dist-info/WHEEL
flake8_module_name-0.2.0.dist-info/entry_points.txt
flake8_module_name-0.2.0.dist-info/top_level.txt
