Metadata-Version: 2.1
Name: flake8-module-name
Version: 0.2.0
Summary: A flake8 plugin for testing PEP-8 conform package and module names.
Home-page: https://github.com/ohjeah/flake8_module_name
Author: Markus Quade
Author-email: info@markusqua.de
License: MIT
Platform: UNKNOWN
Classifier: Programming Language :: Python
Classifier: Programming Language :: Python :: 3.5
Classifier: Programming Language :: Python :: 3.6
